pykCSD-0.1.0.dist-info/WHEEL
pykCSD-0.1.0.dist-info/DESCRIPTION.rst
pykCSD-0.1.0.dist-info/metadata.json
pykCSD-0.1.0.dist-info/RECORD
pykCSD-0.1.0.dist-info/METADATA
pykCSD-0.1.0.dist-info/top_level.txt
pykCSD/potentials.py
pykCSD/pykCSD.py
pykCSD/parameters_utils.py
pykCSD/cross_validation.py
pykCSD/basis_functions.py
pykCSD/validators.py
pykCSD/source_distribution.py
pykCSD/KCSD2D.py
pykCSD/plotting_utils.py
pykCSD/KCSD3D.py
pykCSD/dist_table_utils.py
pykCSD/__init__.py
pykCSD/KCSD1D.py
