Metadata-Version: 2.0
Name: pykCSD
Version: 0.1.0
Summary: UNKNOWN
Home-page: https://github.com/INCF/pykCSD
Author: Grzegorz Parka
Author-email: grzegorz.parka@gmail.com
License: BSD
Keywords: pykCSD,kernel current source denisty
Platform: UNKNOWN
Classifier: Development Status :: 2 - Pre-Alpha
Classifier: Intended Audience :: Developers
Classifier: Intended Audience :: Science/Research
Classifier: Topic :: Scientific/Engineering :: Bio-Informatics
Classifier: License :: OSI Approved :: BSD License
Classifier: Natural Language :: English
Classifier: Programming Language :: Python :: 2.7
Requires-Dist: numpy
Requires-Dist: scipy
Requires-Dist: scikit-learn
